Metadata-Version: 1.1
Name: Kivy-Garden
Version: 0.1.4
Summary: Garden tool fir kivy flowers.
Home-page: https://github.com/kivy-garden/garden
Author: kivy Team
Author-email: akshayaurora@kivy.org
License: MIT
Download-URL: https://github.com/kivy-garden/garden/tarball/0.1.4
Keywords: kivy garden widgets graph development
Platform: UNKNOWN
Classifier: Development Status :: 5 - Production/Stable
Classifier: Intended Audience :: Developers
Classifier: Topic :: Software Development :: Build Tools
Classifier: License :: OSI Approved :: MIT License
Classifier: Programming Language :: Python :: 2
Classifier: Programming Language :: Python :: 2.6
Classifier: Programming Language :: Python :: 2.7
Classifier: Programming Language :: Python :: 3
Classifier: Programming Language :: Python :: 3.2
Classifier: Programming Language :: Python :: 3.3
Classifier: Programming Language :: Python :: 3.4
